Full.v

`timescale 1ns / 1ps

module Top_tb;

    reg clk; // Clock signal
    reg reset; // Reset signal
    wire [15:0] writeData; // Data to be written
    wire [15:0] DataAdr; // Data memory address
    wire memwrite; // Memory write signal

    // Instantiate the Unit Under Test (UUT)
    Top uut (
        .clk(clk),
        .reset(reset),
        .writeData(writeData),
        .DataAdr(DataAdr),
        .memwrite(memwrite)
    );

    // Clock generation: toggle every 5ns for a 10ns period
    always #5 clk = ~clk;
    always begin
        #5;
        if (uut.instr == 16'b1111111111111111) begin
            $display("Successfully Exited");
            uut.imem.print_memory();
            uut.dmem.printMemory();
            $finish;
        end
        if(uut.instr == 0) begin
            $display("PC = %0b", uut.PC);
            $display("Invalid Instruction ..... Terminating!");
            uut.imem.print_memory();
            uut.dmem.printMemory();
            $finish;// Terminate the simulation
        end
    end 

    initial begin
        // Initialize signals
        clk = 0;
        reset = 0;

        // Dump waveforms to a VCD file
        $dumpfile("waveform.vcd"); // Specify VCD file name
        $dumpvars(0, Top_tb); // Dump all signals in the module hierarchy

        // Apply reset
        reset = 1; // Assert reset
        #10;
        reset = 0; // Deassert reset

        // Run simulation for a specified duration
        #5000; // Let the simulation run for 500ns
         // Print memory contents
            uut.imem.print_memory();
            uut.dmem.printMemory();
        

        $finish; // End simulation
    end

endmodule



module Top(input clk, 
    input reset, 
    output [15:0] writeData, 
    output [15: 0] DataAdr, 
    output memwrite); 
    wire [15:0] PC, instr, readData;
    MainProcessor p1(clk,reset, PC, instr, memwrite, readData, DataAdr, writeData);
    InstructionMemory imem(PC,instr);
    DataMemory dmem(DataAdr,writeData,memwrite,clk,readData);
endmodule

module MainProcessor(
    input clk, 
    input rst, 
    output [15:0] PC, 
    input [15:0] instr, 
    output WriteToMEM, 
    input [15:0] readData,
    output [15:0]AluOut, 
    output [15: 0] WriteData);

    wire ForSignal, UpdateRR, JMP, SelectPCSrc, Load, Rtype, Logical, WriteToReg,IMM, BNE,Branch;
    wire [2:0] AluControl;
    controller c(instr[15:12],instr[2:0],ForSignal, UpdateRR, JMP, SelectPCSrc, Load, Rtype, Logical, WriteToReg,IMM, BNE,Branch,WriteToMEM,AluControl);
    DataPath data(clk, rst, SelectPCSrc, ForSignal, UpdateRR, JMP, Load, Rtype, Logical, WriteToReg, IMM, BNE, Branch, WriteToMEM, AluControl, readData, instr, PC, AluOut, WriteData);

endmodule

module InstructionMemory(input [15:0] A, output reg [15:0] RD);

    reg [15:0] memory [0:63];  //memory has 64 locations and each cell is 16 bits

    initial begin
    $readmemb("Instruction.txt", memory); //this will read the file to initialize the memory
    end



    always @* begin
        RD = memory[A];
    end
    task print_memory;
    integer i;
    begin
        // Loop through all memory locations and print the content
        $display("\n----------Instruction Memory-----------------");
        for (i = 0; i < 64; i = i + 1) begin
              // Set the address to i
            #1;  // Wait for the memory to resolve
            $display("MemoryInstr[%0d] = %b", i,memory[i] );  // Print memory content
        end
        $display("----------------------------------------------");
    end
    endtask
endmodule

module controller(
    input logic [3:0] opcode, 
    input [2:0] func, 
    output ForSignal, 
    output UpdateRR, 
    output JMP, 
    output SelectPCSrc,
	output Load, 
	output RType,
	output Logical, 
	output WriteToReg, 
	output IMM,
	output BNE, 
	output Branch, 
	output WriteToMEM,
	output [2:0] AluControl);
	
	wire [1:0] aluop;
	mainDec main1(opcode, func, ForSignal, UpdateRR, JMP, SelectPCSrc, Load, RType, Logical, WriteToReg, IMM, BNE, Branch, WriteToMEM, aluop);
	AluDecoder alu1(aluop, func, AluControl);	  

endmodule

`define RTYPE   4'b0000
`define ANDI    4'b0010
`define ADDI    4'b0011
`define BEQ     4'b0110
`define BNE     4'b0111
`define FOR     4'b1000
`define LOAD    4'b0100
`define STORE   4'b0101
`define JMP     3'b000
`define CALL    3'b001
`define RET  3'b010
`define JTYPE   4'b0001

module mainDec(input [3:0] opcode, input [2:0]func, output ForSignal, output UpdateRR, output JMP, output SelectPCSrc,
	output Load, 
	output RType,
	output Logical, 
	output WriteToReg, 
	output IMM,
	output BNE, 
	output Branch, 
	output WriteToMEM,
	output [1:0] AluOp);	   

    assign ForSignal = (opcode == `FOR);
    assign UpdateRR = ((opcode == `FOR) ^ (opcode == `JTYPE && func == `CALL));
    assign JMP = (opcode == `JTYPE && (func == `CALL ^  func == `JMP));
    assign SelectPCSrc = (opcode == `JTYPE);
    assign Load = (opcode ==`LOAD);
    assign RType = (opcode == `RTYPE); 
    assign Logical = (opcode == `ANDI);
    assign WriteToReg = (opcode != `JTYPE && opcode != `BEQ && opcode != `BNE && opcode != `STORE);
    assign IMM = (opcode == `ADDI ^ opcode ==`ANDI ^ opcode == `LOAD ^ opcode == `STORE);
    assign BNE = (opcode == `BNE);
    assign Branch = (opcode == `BEQ ^ opcode == `BNE);
    assign WriteToMEM = (opcode == `STORE);
    assign AluOp = (opcode == `RTYPE) ? 2'b00 :                  // RTYPE
                   (opcode == `ANDI)  ? 2'b10 :                  // ANDI
                   (opcode == `ADDI ^ opcode == `LOAD ^ opcode == `STORE)  ? 2'b01 :                  // ADDI
                   2'b11;       

endmodule


module AluDecoder(
    input logic [1:0] aluop,
    input logic [2:0] func,
    output logic [2:0] alucontrol
);
    always @* begin 
        case (aluop)
            2'b10: alucontrol = 3'b000; //and
            2'b01: alucontrol = 3'b001; //add
            2'b11: alucontrol = 3'b010;  //sub
            default: begin
                case (func)
                    3'b000: alucontrol = 3'b000;  //and
                    3'b001: alucontrol = 3'b001;  //add
                    3'b010: alucontrol = 3'b010;  //sub
                    3'b011: alucontrol = 3'b011;  //ShiftLeftLogical
                    3'b100: alucontrol = 3'b100;  //ShiftRight
                    default: alucontrol = 3'bxxx;
                endcase
            end
        endcase
    end
endmodule

module DataMemory(input [15:0] A, input [15:0] WD, input WE, CLK, output reg [15:0] RD);

     reg [15:0] memory [0:63];  //memory has 64 locations and each cell is 16 bits

        initial begin  
        $readmemb("Data.txt", memory); //this will read the file to initialize the memory
        end
        always @(negedge CLK) begin
        RD = memory[A];  // Read memory at address A
        end

     always @ (posedge CLK) begin
         if (WE == 1)
             begin
                    memory[A] = WD;
             end
        end 
  // Task to print memory contents
    task printMemory;
        integer i;
        begin
            $display("\n----- Memory Contents -----");
            for (i = 0; i < 64; i = i + 1) begin
                $display("Memory[%0d] = %0d", i, $signed(memory[i]));
            end
            $display("---------------------------");
        end
    endtask

endmodule

module RegisterFile (
input clk, // Clock Signal
input rst, // Reset Signal
input WE3, // Write Enable Signal
input [15:0] WD3, // Write Data
input [2:0] A1, // Src. Address 1
input [2:0] A2, // Src. Address 2
input [2:0] A3, // Dst. Address
output reg [15:0] RD1, // Read Data Register
output reg [15:0] RD2 // Read Data Register
);

    integer i; // Loop Variable

    // Register File
    reg [15:0] RegisterFile [7:0];

    // Write Operation
    always @(posedge clk or posedge rst) begin
        if (rst) begin
            // Reset all registers to 0
            for (i = 0; i < 8; i = i + 1) begin
                RegisterFile[i] <= 16'b0;
            end
        end
        else if (WE3) begin
            RegisterFile[A3] <= WD3;
        end
    end

    // Read Operation
    always @* begin
        RD1 = RegisterFile[A1];
        RD2 = RegisterFile[A2];
    end

endmodule


module RR(
    input clk,
    input rst,
    input [15:0] in,
    output reg [15:0] out
);

    always @(posedge clk or posedge rst) begin
        if (rst) begin
            out <= 16'h0000;
        end else begin
            out <= in;
        end
    end
endmodule

module ALU(
    input [15:0] R1, 
    input [15:0] R2, 
    input logic [2:0] alucontrol, 
    output logic [15:0] Answer,
    output logic zeroflag
);
    always @* begin 
        case (alucontrol)
            3'b000: Answer = R1 & R2;   // AND
            3'b001: Answer = R1 + R2;  // Add
            3'b010: Answer = R2 - R1;  // Subtract
            3'b011: Answer = R2 << R1; // Shift Left Logical
            3'b100: Answer = R2 >> R1; // Shift Right Logical
            default: Answer = 16'bxxxxxxxxxxxxxx; // Default to addition
        endcase

        // Set zeroflag if the result is 0
        if (Answer == 0)
            zeroflag = 1; 
        else 
            zeroflag = 0; 
    end
endmodule 

module Mux4x2(
    input [15:0] in1,
    input [15:0] in2,
    input [15:0] in3,
    input [15:0] in4,
    input [1:0] sel,
    output [15:0] out
);

    reg [15:0] mux_out;

    always @(*) begin
        case(sel)
            2'b00: mux_out = in1;
            2'b01: mux_out = in2;
            2'b10: mux_out = in3;
            2'b11: mux_out = in4;
        endcase
    end

    assign out = mux_out;

endmodule

module Mux2x1 (
    input Sel, // Select Signal
    input [15: 0] I0, // Input 0
    input [15: 0] I1, // Input 1
    output reg [15: 0] out // Output Result
);

    always @ (*) begin
        if (Sel == 0) begin 
            out = I0;
        end
        else begin 
            out = I1;
        end
    end
endmodule

module NOT_Gate(
    input in,
    output out
);

    assign out = ~in;

endmodule

module AND_Gate(
    input In1,
    input In2,
    output out
);

    assign out = In1 & In2;

endmodule

module Extender(input [5:0] in, output [15:0] out, input logical_signal);
    // if logical signal 1 then unsign extend
    // if logical signal 0 then sign extend

    wire [15:0] sign_extended;
    wire [15:0] unsign_extended;

    assign sign_extended = {{10{in[5]}}, in};
    assign unsign_extended = {{10{1'b0}}, in};


    assign out = logical_signal ? unsign_extended : sign_extended;


endmodule







module Adder(input [15:0] In1, input [15:0] In2, output [15:0] out);
    assign out    = In1 + In2;
endmodule


module Concat(input [6:0] in1, input [8:0] in2, output [15:0] out);
    assign out = {in1, in2};
endmodule



module PC (
    input clk,
    input rst,
    input [15:0] pc_next,
    output reg [15:0] pc_out
);

    always @(posedge clk or posedge rst) begin
        if (rst) begin
            pc_out <= 16'h0000;
        end else begin
            pc_out <= pc_next;
        end
    end

endmodule
module DataPath(
    input clk,
    input rst,
    input slect_pc_src,
    input for_signal,
    input update_rr,
    input jmp_target,
    input load,
    input r_type,
    input logical_signal,
    input write_to_reg,
    input imm,
    input bne,
    input branch_signal,
    input write_to_mem,
    input [2:0] alu_control,
    input [15:0] RD, // data from memory
    input [15: 0] inst_in,
    output [15:0] pc_out,
    output [15:0] alu_out,
    output [15:0] write_on_memory_data
);

    // PC Handling
    wire [15: 0] pc_next;

    PC pc(
        .clk(clk),
        .rst(rst),
        .pc_next(pc_next),
        .pc_out(pc_out)
    );
    
    
    // JMP Target
    wire [15: 0] jmp_target_extended;
    // Branch
    wire [15: 0] branch_extended;
    // PC + 1
    wire [15: 0] pc_plus_1;

     // calculate pc by Adder module
    Adder adder(
        .In1(pc_out),
        .In2(16'h0001),
        .out(pc_plus_1)
    );

    // Concat module for jmp_target
    Concat concat_jmp_target(
        .in1(pc_plus_1[15: 9]),
        .in2(inst_in[11: 3]),
        .out(jmp_target_extended)
    );

    // Extender module for branch (sign extend)
    Extender extender_branch(
        .in(inst_in[5: 0]),
        .out(branch_extended),
        .logical_signal(logical_signal)
    );


    // AND between not_zero and for_signal by AND module
    wire and_out;
    // not_zero signal
    wire not_zero;

    NOT_Gate not_1(
        .in(zero_signal),
        .out(not_zero)
    );

    AND_Gate and_1(
        .In1(not_zero),
        .In2(for_signal),
        .out(and_out)
    );

    // MUX for choosing Zero or not zero
    wire mux_zero_out;

    Mux2x1 mux_zero(
        .I0(zero_signal),
        .I1(not_zero),
        .Sel(bne),
        .out(mux_zero_out)
    );

    // AND between branch and mux_zero by AND module
    wire and_out_2;
    AND_Gate and_2(
        .In1(mux_zero_out),
        .In2(branch_signal),
        .out(and_out_2)
    );
    // Register file

    // Mux2x1 for choosing (A1)
    wire [15: 0] mux_a1_out;
    Mux2x1 mux_a1(
        .I0(inst_in[11: 9]),
        .I1(inst_in[5: 3]),
        .Sel(r_type),
        .out(mux_a1_out)
    );
    // Mux2x1 for choosing (A3)
    wire [15: 0] mux_a3_out;
    Mux2x1 mux_a3(
        .I0(inst_in[8: 6]),
        .I1(inst_in[11: 9]),
        .Sel(r_type),
        .out(mux_a3_out)
    );
    
    // reg_out_2 + -1
    wire [15: 0] reg_out_2_minus_1;
    Adder adder_reg_out_2_minus_1(
        .In1(reg_out2),
        .In2(16'hFFFF),
        .out(reg_out_2_minus_1)
    );
    
    // ALU

    // Mux2x1 for choosing (R1)
    wire [15: 0] mux_r1_out;
    Mux2x1 mux_r1(
        .I0(reg_out1),
        .I1(16'h0000),
        .Sel(for_signal),
        .out(mux_r1_out)
    );
    // Mux2x1 for choosing (R2)
    wire [15: 0] mux_r2_out;
    Mux2x1 mux_r2(
        .I0(reg_out2),
        .I1(branch_extended),
        .Sel(imm),
        .out(mux_r2_out)
    );

    wire zero_signal_alu;
    ALU alu(
        .R1(mux_r1_out),
        .R2(mux_r2_out),
        .alucontrol(alu_control),
        .Answer(alu_out),
        .zeroflag(zero_signal_alu)
    );

    // assign zero_signal = zero_signal_alu;
    assign zero_signal = zero_signal_alu;
    assign write_on_memory_data = reg_out2;

    // Mux2x1 for choosing (WD3)
    wire [15: 0] mux_wd3_1_out;
    Mux2x1 mux_wd3_1(
        .I0(alu_out),
        .I1(reg_out_2_minus_1),
        .Sel(for_signal),
        .out(mux_wd3_1_out)
    );
    // Mux2x1 for choosing (WD3)
    wire [15: 0] mux_wd3_2_out;
    Mux2x1 mux_wd3(
        .I0(mux_wd3_1_out),
        .I1(RD),
        .Sel(load),
        .out(mux_wd3_2_out)
    );
    wire [15: 0] reg_out1;
    wire [15: 0] reg_out2;  
    RegisterFile reg_file (
        .clk(clk),
        .rst(rst),
        .WE3(write_to_reg),
        .WD3(mux_wd3_2_out),
        .A1(mux_a1_out[2: 0]),
        .A2(inst_in[8: 6]),
        .A3(mux_a3_out[2: 0]),
        .RD1(reg_out1),
        .RD2(reg_out2)
);
    // Mux2x1 for choosing (pc + 1 or Rs (for_loop instruction))
    wire [15: 0] mux_out;
    Mux2x1 mux_pc_src(
        .I0(pc_plus_1),
        .I1(reg_out1),
        .Sel(and_out),
        .out(mux_out)
    );


    // Mux4x2 for choosing next pc
    
    // add branch and pc + 1
    wire [15: 0] branch_extended_add_pc_plus_1;
    Adder adder_branch_pc_plus_1(
        .In1(pc_out),
        .In2(branch_extended),
        .out(branch_extended_add_pc_plus_1)
    );
    // RR

    
    // RR current value
    wire [15: 0] rr_current;
    RR rr(
        .clk(clk),
        .rst(rst),
        .in(mux_rr_2_out),
        .out(rr_current)
    );

    // Mux 2x1 for choosing RR input 1
    wire [15: 0] mux_rr_1_out;
    Mux2x1 mux_rr_1(
        .I0(pc_plus_1),
        .I1(pc_out),
        .Sel(for_signal),
        .out(mux_rr_1_out)
    );
    // Mux2x1 to choose RR input
    wire [15: 0] mux_rr_2_out;
    Mux2x1 mux_rr_2(
        .I0(rr_current),
        .I1(mux_rr_1_out),
        .Sel(update_rr),
        .out(mux_rr_2_out)
    );

    // Mux2x1 to choose in3
    wire [15: 0] mux_in3_out;
    Mux2x1 mux_in3(
        .I0(rr_current),
        .I1(jmp_target_extended),
        .Sel(jmp_target),
        .out(mux_in3_out)
    );
    wire [15: 0] mux_next_pc_out;
    Mux4x2 mux_next_pc(
        .in1(mux_out),
        .in2(branch_extended_add_pc_plus_1),
        .in3(mux_in3_out),
        .in4(16'h0000),// nothing
        .sel({slect_pc_src, and_out_2}),
        .out(mux_next_pc_out)
    );  

    assign pc_next = mux_next_pc_out;

endmodule

waveform.vcd
$date
	Tue Jan 07 20:18:22 2025
$end
$version
	Icarus Verilog
$end
$timescale
	1ps
$end
$scope module Top_tb $end
$var wire 16 ! writeData [15:0] $end
$var wire 1 " memwrite $end
$var wire 16 # DataAdr [15:0] $end
$var reg 1 $ clk $end
$var reg 1 % reset $end
$scope module uut $end
$var wire 1 $ clk $end
$var wire 1 % reset $end
$var wire 16 & writeData [15:0] $end
$var wire 16 ' readData [15:0] $end
$var wire 1 " memwrite $end
$var wire 16 ( instr [15:0] $end
$var wire 16 ) PC [15:0] $end
$var wire 16 * DataAdr [15:0] $end
$scope module dmem $end
$var wire 1 $ CLK $end
$var wire 1 " WE $end
$var wire 16 + WD [15:0] $end
$var wire 16 , A [15:0] $end
$var reg 16 - RD [15:0] $end
$scope task printMemory $end
$var integer 32 . i [31:0] $end
$upscope $end
$upscope $end
$scope module imem $end
$var wire 16 / A [15:0] $end
$var reg 16 0 RD [15:0] $end
$scope task print_memory $end
$var integer 32 1 i [31:0] $end
$upscope $end
$upscope $end
$scope module p1 $end
$var wire 1 $ clk $end
$var wire 16 2 instr [15:0] $end
$var wire 16 3 readData [15:0] $end
$var wire 1 % rst $end
$var wire 1 4 WriteToReg $end
$var wire 1 " WriteToMEM $end
$var wire 16 5 WriteData [15:0] $end
$var wire 1 6 UpdateRR $end
$var wire 1 7 SelectPCSrc $end
$var wire 1 8 Rtype $end
$var wire 16 9 PC [15:0] $end
$var wire 1 : Logical $end
$var wire 1 ; Load $end
$var wire 1 < JMP $end
$var wire 1 = IMM $end
$var wire 1 > ForSignal $end
$var wire 1 ? Branch $end
$var wire 1 @ BNE $end
$var wire 16 A AluOut [15:0] $end
$var wire 3 B AluControl [2:0] $end
$scope module c $end
$var wire 3 C func [2:0] $end
$var wire 4 D opcode [3:0] $end
$var wire 2 E aluop [1:0] $end
$var wire 1 4 WriteToReg $end
$var wire 1 " WriteToMEM $end
$var wire 1 6 UpdateRR $end
$var wire 1 7 SelectPCSrc $end
$var wire 1 8 RType $end
$var wire 1 : Logical $end
$var wire 1 ; Load $end
$var wire 1 < JMP $end
$var wire 1 = IMM $end
$var wire 1 > ForSignal $end
$var wire 1 ? Branch $end
$var wire 1 @ BNE $end
$var wire 3 F AluControl [2:0] $end
$scope module alu1 $end
$var wire 3 G func [2:0] $end
$var wire 2 H aluop [1:0] $end
$var reg 3 I alucontrol [2:0] $end
$upscope $end
$scope module main1 $end
$var wire 1 ? Branch $end
$var wire 1 = IMM $end
$var wire 1 < JMP $end
$var wire 1 6 UpdateRR $end
$var wire 1 4 WriteToReg $end
$var wire 3 J func [2:0] $end
$var wire 4 K opcode [3:0] $end
$var wire 1 " WriteToMEM $end
$var wire 1 7 SelectPCSrc $end
$var wire 1 8 RType $end
$var wire 1 : Logical $end
$var wire 1 ; Load $end
$var wire 1 > ForSignal $end
$var wire 1 @ BNE $end
$var wire 2 L AluOp [1:0] $end
$upscope $end
$upscope $end
$scope module data $end
$var wire 16 M RD [15:0] $end
$var wire 3 N alu_control [2:0] $end
$var wire 1 @ bne $end
$var wire 1 ? branch_signal $end
$var wire 1 $ clk $end
$var wire 1 > for_signal $end
$var wire 1 = imm $end
$var wire 16 O inst_in [15:0] $end
$var wire 1 < jmp_target $end
$var wire 1 ; load $end
$var wire 1 : logical_signal $end
$var wire 16 P pc_next [15:0] $end
$var wire 1 8 r_type $end
$var wire 1 % rst $end
$var wire 1 7 slect_pc_src $end
$var wire 1 6 update_rr $end
$var wire 16 Q write_on_memory_data [15:0] $end
$var wire 1 " write_to_mem $end
$var wire 1 4 write_to_reg $end
$var wire 1 R zero_signal $end
$var wire 1 S zero_signal_alu $end
$var wire 16 T rr_current [15:0] $end
$var wire 16 U reg_out_2_minus_1 [15:0] $end
$var wire 16 V reg_out2 [15:0] $end
$var wire 16 W reg_out1 [15:0] $end
$var wire 16 X pc_plus_1 [15:0] $end
$var wire 16 Y pc_out [15:0] $end
$var wire 1 Z not_zero $end
$var wire 1 [ mux_zero_out $end
$var wire 16 \ mux_wd3_2_out [15:0] $end
$var wire 16 ] mux_wd3_1_out [15:0] $end
$var wire 16 ^ mux_rr_2_out [15:0] $end
$var wire 16 _ mux_rr_1_out [15:0] $end
$var wire 16 ` mux_r2_out [15:0] $end
$var wire 16 a mux_r1_out [15:0] $end
$var wire 16 b mux_out [15:0] $end
$var wire 16 c mux_next_pc_out [15:0] $end
$var wire 16 d mux_in3_out [15:0] $end
$var wire 16 e mux_a3_out [15:0] $end
$var wire 16 f mux_a1_out [15:0] $end
$var wire 16 g jmp_target_extended [15:0] $end
$var wire 16 h branch_extended_add_pc_plus_1 [15:0] $end
$var wire 16 i branch_extended [15:0] $end
$var wire 1 j and_out_2 $end
$var wire 1 k and_out $end
$var wire 16 l alu_out [15:0] $end
$scope module adder $end
$var wire 16 m In2 [15:0] $end
$var wire 16 n out [15:0] $end
$var wire 16 o In1 [15:0] $end
$upscope $end
$scope module adder_branch_pc_plus_1 $end
$var wire 16 p out [15:0] $end
$var wire 16 q In2 [15:0] $end
$var wire 16 r In1 [15:0] $end
$upscope $end
$scope module adder_reg_out_2_minus_1 $end
$var wire 16 s In2 [15:0] $end
$var wire 16 t out [15:0] $end
$var wire 16 u In1 [15:0] $end
$upscope $end
$scope module alu $end
$var wire 3 v alucontrol [2:0] $end
$var wire 16 w R2 [15:0] $end
$var wire 16 x R1 [15:0] $end
$var reg 16 y Answer [15:0] $end
$var reg 1 S zeroflag $end
$upscope $end
$scope module and_1 $end
$var wire 1 > In2 $end
$var wire 1 k out $end
$var wire 1 Z In1 $end
$upscope $end
$scope module and_2 $end
$var wire 1 [ In1 $end
$var wire 1 ? In2 $end
$var wire 1 j out $end
$upscope $end
$scope module concat_jmp_target $end
$var wire 7 z in1 [6:0] $end
$var wire 9 { in2 [8:0] $end
$var wire 16 | out [15:0] $end
$upscope $end
$scope module extender_branch $end
$var wire 6 } in [5:0] $end
$var wire 1 : logical_signal $end
$var wire 16 ~ unsign_extended [15:0] $end
$var wire 16 !" sign_extended [15:0] $end
$var wire 16 "" out [15:0] $end
$upscope $end
$scope module mux_a1 $end
$var wire 16 #" I0 [15:0] $end
$var wire 16 $" I1 [15:0] $end
$var wire 1 8 Sel $end
$var reg 16 %" out [15:0] $end
$upscope $end
$scope module mux_a3 $end
$var wire 16 &" I0 [15:0] $end
$var wire 16 '" I1 [15:0] $end
$var wire 1 8 Sel $end
$var reg 16 (" out [15:0] $end
$upscope $end
$scope module mux_in3 $end
$var wire 16 )" I1 [15:0] $end
$var wire 1 < Sel $end
$var wire 16 *" I0 [15:0] $end
$var reg 16 +" out [15:0] $end
$upscope $end
$scope module mux_next_pc $end
$var wire 16 ," in2 [15:0] $end
$var wire 16 -" in3 [15:0] $end
$var wire 16 ." in4 [15:0] $end
$var wire 16 /" out [15:0] $end
$var wire 2 0" sel [1:0] $end
$var wire 16 1" in1 [15:0] $end
$var reg 16 2" mux_out [15:0] $end
$upscope $end
$scope module mux_pc_src $end
$var wire 16 3" I0 [15:0] $end
$var wire 1 k Sel $end
$var wire 16 4" I1 [15:0] $end
$var reg 16 5" out [15:0] $end
$upscope $end
$scope module mux_r1 $end
$var wire 16 6" I1 [15:0] $end
$var wire 1 > Sel $end
$var wire 16 7" I0 [15:0] $end
$var reg 16 8" out [15:0] $end
$upscope $end
$scope module mux_r2 $end
$var wire 16 9" I1 [15:0] $end
$var wire 1 = Sel $end
$var wire 16 :" I0 [15:0] $end
$var reg 16 ;" out [15:0] $end
$upscope $end
$scope module mux_rr_1 $end
$var wire 16 <" I0 [15:0] $end
$var wire 1 > Sel $end
$var wire 16 =" I1 [15:0] $end
$var reg 16 >" out [15:0] $end
$upscope $end
$scope module mux_rr_2 $end
$var wire 16 ?" I1 [15:0] $end
$var wire 1 6 Sel $end
$var wire 16 @" I0 [15:0] $end
$var reg 16 A" out [15:0] $end
$upscope $end
$scope module mux_wd3 $end
$var wire 16 B" I1 [15:0] $end
$var wire 1 ; Sel $end
$var wire 16 C" I0 [15:0] $end
$var reg 16 D" out [15:0] $end
$upscope $end
$scope module mux_wd3_1 $end
$var wire 16 E" I0 [15:0] $end
$var wire 16 F" I1 [15:0] $end
$var wire 1 > Sel $end
$var reg 16 G" out [15:0] $end
$upscope $end
$scope module mux_zero $end
$var wire 16 H" I0 [15:0] $end
$var wire 16 I" I1 [15:0] $end
$var wire 1 @ Sel $end
$var reg 16 J" out [15:0] $end
$upscope $end
$scope module not_1 $end
$var wire 1 R in $end
$var wire 1 Z out $end
$upscope $end
$scope module pc $end
$var wire 1 $ clk $end
$var wire 16 K" pc_next [15:0] $end
$var wire 1 % rst $end
$var reg 16 L" pc_out [15:0] $end
$upscope $end
$scope module reg_file $end
$var wire 3 M" A1 [2:0] $end
$var wire 3 N" A2 [2:0] $end
$var wire 3 O" A3 [2:0] $end
$var wire 16 P" WD3 [15:0] $end
$var wire 1 4 WE3 $end
$var wire 1 $ clk $end
$var wire 1 % rst $end
$var reg 16 Q" RD1 [15:0] $end
$var reg 16 R" RD2 [15:0] $end
$var integer 32 S" i [31:0] $end
$upscope $end
$scope module rr $end
$var wire 1 $ clk $end
$var wire 16 T" in [15:0] $end
$var wire 1 % rst $end
$var reg 16 U" out [15:0] $end
$upscope $end
$upscope $end
$upscope $end
$upscope $end
$upscope $end
$enddefinitions $end
#0
$dumpvars
b0 U"
b0 T"
b1000 S"
b0 R"
b0 Q"
bx P"
b101 O"
b101 N"
b0 M"
b0 L"
b1 K"
b0 J"
b1 I"
b0 H"
b11 G"
b1111111111111111 F"
b11 E"
bx D"
b11 C"
bx B"
b0 A"
b0 @"
b1 ?"
b1 >"
b0 ="
b1 <"
b11 ;"
b0 :"
b11 9"
b0 8"
b0 7"
b0 6"
b1 5"
b0 4"
b1 3"
b1 2"
b1 1"
b0 0"
b1 /"
b0 ."
b0 -"
b11 ,"
b0 +"
b0 *"
b101000 )"
b101 ("
b0 '"
b101 &"
b0 %"
b0 $"
b0 #"
b11 ""
b11 !"
b11 ~
b11 }
b101000 |
b101000 {
b0 z
b11 y
b0 x
b11 w
b1 v
b0 u
b1111111111111111 t
b1111111111111111 s
b0 r
b11 q
b11 p
b0 o
b1 n
b1 m
b11 l
0k
0j
b11 i
b11 h
b101000 g
b0 f
b101 e
b0 d
b1 c
b1 b
b0 a
b11 `
b1 _
b0 ^
b11 ]
bx \
0[
1Z
b0 Y
b1 X
b0 W
b0 V
b1111111111111111 U
b0 T
0S
0R
b0 Q
b1 P
b100000101000011 O
b1 N
bx M
b1 L
b100 K
b11 J
b1 I
b1 H
b11 G
b1 F
b1 E
b100 D
b11 C
b1 B
b11 A
0@
0?
0>
1=
0<
1;
0:
b0 9
08
07
06
b0 5
14
bx 3
b100000101000011 2
bx 1
b100000101000011 0
b0 /
bx .
bx -
b11 ,
b0 +
b11 *
b0 )
b100000101000011 (
bx '
b0 &
1%
0$
b11 #
0"
b0 !
$end
#5000
b1000 S"
1$
#10000
b1111 \
b1111 D"
b1111 P"
b1111 '
b1111 -
b1111 3
b1111 M
b1111 B"
0$
0%
#15000
b1 B
b1 F
b1 I
b1 N
b1 v
b1 E
b1 H
b1 L
b110 ]
b110 C"
b110 G"
b110 #
b110 *
b110 ,
b110 A
b110 l
b110 y
b110 E"
b110 `
b110 w
b110 ;"
b110 \
b110 D"
b110 P"
04
1=
b110 i
b110 q
b110 ""
b110 9"
0;
1"
b101 D
b101 K
b110 C
b110 G
b110 J
b110 !"
b110 ~
b110 }
b10 P
b10 K"
b10 c
b10 /"
b10 2"
b10 b
b10 1"
b10 5"
b101000101000110 (
b101000101000110 0
b101000101000110 2
b101000101000110 O
b10 _
b10 >"
b10 ?"
b1110 U
b1110 t
b1110 F"
b1111 !
b1111 &
b1111 +
b1111 5
b1111 Q
b1111 V
b1111 u
b1111 :"
b1111 R"
b111 h
b111 p
b111 ,"
b10 X
b10 n
b10 3"
b10 <"
b1 )
b1 /
b1 9
b1 Y
b1 o
b1 r
b1 ="
b1 L"
1$
#20000
b10 '
b10 -
b10 3
b10 M
b10 B"
0$
#25000
b1 B
b1 F
b1 I
b1 N
b1 v
0[
b1 E
b1 H
b1 L
b0 J"
b1 I"
1Z
b1 ]
b1 C"
b1 G"
b0 H"
0R
0S
b1 #
b1 *
b1 ,
b1 A
b1 l
b1 y
b1 E"
b11 O"
b1 `
b1 w
b1 ;"
b10 \
b10 D"
b10 P"
14
1=
b1 i
b1 q
b1 ""
b1 9"
b11 e
b11 ("
b1111111111111111 U
b1111111111111111 t
b1111111111111111 F"
b0 !
b0 &
b0 +
b0 5
b0 Q
b0 V
b0 u
b0 :"
b0 R"
1;
0"
b100 D
b100 K
b1 C
b1 G
b1 J
b11000 g
b11000 |
b11000 )"
b11000 {
b1 !"
b1 ~
b1 }
b11 &"
b11 N"
b11 P
b11 K"
b11 c
b11 /"
b11 2"
b11 b
b11 1"
b11 5"
b100000011000001 (
b100000011000001 0
b100000011000001 2
b100000011000001 O
b11 _
b11 >"
b11 ?"
b11 h
b11 p
b11 ,"
b11 X
b11 n
b11 3"
b11 <"
b10 )
b10 /
b10 9
b10 Y
b10 o
b10 r
b10 ="
b10 L"
1$
#30000
0$
#35000
b1 B
b1 F
b1 I
b1 N
b1 v
b1 E
b1 H
b1 L
b1001 ]
b1001 C"
b1001 G"
b1001 #
b1001 *
b1001 ,
b1001 A
b1001 l
b1001 y
b1001 E"
b1001 `
b1001 w
b1001 ;"
b1001 \
b1001 D"
b1001 P"
04
1=
b1001 i
b1001 q
b1001 ""
b1001 9"
0;
1"
b101 D
b101 K
b11001 g
b11001 |
b11001 )"
b11001 {
b1001 !"
b1001 ~
b1001 }
b1 $"
b100 P
b100 K"
b100 c
b100 /"
b100 2"
b100 b
b100 1"
b100 5"
b101000011001001 (
b101000011001001 0
b101000011001001 2
b101000011001001 O
b100 _
b100 >"
b100 ?"
b1 U
b1 t
b1 F"
b10 !
b10 &
b10 +
b10 5
b10 Q
b10 V
b10 u
b10 :"
b10 R"
b1100 h
b1100 p
b1100 ,"
b100 X
b100 n
b100 3"
b100 <"
b11 )
b11 /
b11 9
b11 Y
b11 o
b11 r
b11 ="
b11 L"
1$
#40000
b0 '
b0 -
b0 3
b0 M
b0 B"
0$
